README.md
onnx_model_speed_test.py
setup.py
apstone/__init__.py
apstone/model_base.py
apstone.egg-info/PKG-INFO
apstone.egg-info/SOURCES.txt
apstone.egg-info/dependency_links.txt
apstone.egg-info/requires.txt
apstone.egg-info/top_level.txt
apstone/model_convert/__init__.py
apstone/model_convert/detectron2_model_export.py
apstone/model_convert/modelscope_ali_2_onnx.py
apstone/model_convert/onnx2simple2trt.py
apstone/model_convert/onnx2trt.py
apstone/model_convert/show_pb_nodes.py
apstone/model_convert/tf2pb2onnx.py
apstone/model_convert/torch2any.py
apstone/model_edit/__init__.py
apstone/model_edit/torch_model_edit.py
apstone/onnx_tools/convert_onnx_input_shape.py
apstone/onnx_tools/onnx_merge.py
apstone/onnx_tools/remove_initializer_from_input.py
apstone/onnx_tools/symbolic_shape_infer.py
apstone/wrappers/__init__.py
apstone/wrappers/llm_wrapper/llm_model.py
apstone/wrappers/mmlab_wrapper/__init__.py
apstone/wrappers/mmlab_wrapper/bbox_detector_mmdet.py
apstone/wrappers/mmlab_wrapper/kp_detector_mmpose.py
apstone/wrappers/mmlab_wrapper/utils.py
apstone/wrappers/onnx_wrapper/__init__.py
apstone/wrappers/onnx_wrapper/onnx_model.py
apstone/wrappers/onnx_wrapper/onnx_model_picklable.py
apstone/wrappers/tjm_wrapper/__init__.py
apstone/wrappers/tjm_wrapper/tjm_model.py
apstone/wrappers/trt_wrapper/__init__.py
apstone/wrappers/trt_wrapper/trt_wrapper_mmdeploy.py
apstone/wrappers/trt_wrapper/trt_wrapper_self.py