Metadata-Version: 2.1
Name: apstone
Version: 0.0.8
Summary: ai_power base stone
Home-page: https://github.com/ykk648/apstone
Author: ykk648
Author-email: ykk648@gmail.com
Project-URL: Bug Tracker, https://github.com/ykk648/apstone/issues
Classifier: Programming Language :: Python :: 3
Classifier: License :: OSI Approved :: GNU General Public License v3 (GPLv3)
Classifier: Operating System :: OS Independent
Requires-Dist: cv2box
Provides-Extra: light
Provides-Extra: full
Requires-Dist: apscheduler; extra == "full"
Requires-Dist: numexpr; extra == "full"
Requires-Dist: h5py; extra == "full"
Requires-Dist: yaml; extra == "full"
